archivviewer/__init__.py
archivviewer/archivviewer.py
archivviewer/forms/__init__.py
archivviewer/forms/archivviewer_ui.py
archivviewer/forms/avconfig_ui.py
ArchivViewer-3.dist-info/LICENSE.txt
ArchivViewer-3.dist-info/METADATA
ArchivViewer-3.dist-info/WHEEL
ArchivViewer-3.dist-info/entry_points.txt
ArchivViewer-3.dist-info/top_level.txt
ArchivViewer-3.dist-info/RECORD
